LICENSE
README.md
setup.py
litex_boards/__init__.py
litex_boards.egg-info/PKG-INFO
litex_boards.egg-info/SOURCES.txt
litex_boards.egg-info/dependency_links.txt
litex_boards.egg-info/requires.txt
litex_boards.egg-info/top_level.txt
litex_boards/platforms/__init__.py
litex_boards/platforms/adi_adrv2crr_fmc.py
litex_boards/platforms/adi_plutosdr.py
litex_boards/platforms/alchitry_au.py
litex_boards/platforms/alchitry_cu.py
litex_boards/platforms/alchitry_mojo.py
litex_boards/platforms/aliexpress_xc7k420t.py
litex_boards/platforms/aliexpress_xc7k70t.py
litex_boards/platforms/alinx_ax7010.py
litex_boards/platforms/alinx_axu2cga.py
litex_boards/platforms/analog_pocket.py
litex_boards/platforms/antmicro_artix_dc_scm.py
litex_boards/platforms/antmicro_datacenter_ddr4_test_board.py
litex_boards/platforms/antmicro_lpddr4_test_board.py
litex_boards/platforms/antmicro_sdi_mipi_video_converter.py
litex_boards/platforms/arduino_mkrvidor4000.py
litex_boards/platforms/avalanche.py
litex_boards/platforms/avnet_aesku40.py
litex_boards/platforms/berkeleylab_marble.py
litex_boards/platforms/berkeleylab_marblemini.py
litex_boards/platforms/camlink_4k.py
litex_boards/platforms/colorlight_5a_75b.py
litex_boards/platforms/colorlight_5a_75e.py
litex_boards/platforms/colorlight_i5.py
litex_boards/platforms/colorlight_i5a_907.py
litex_boards/platforms/colorlight_i9plus.py
litex_boards/platforms/decklink_intensity_pro_4k.py
litex_boards/platforms/decklink_mini_4k.py
litex_boards/platforms/decklink_quad_hdmi_recorder.py
litex_boards/platforms/digilent_arty.py
litex_boards/platforms/digilent_arty_s7.py
litex_boards/platforms/digilent_arty_z7.py
litex_boards/platforms/digilent_atlys.py
litex_boards/platforms/digilent_basys3.py
litex_boards/platforms/digilent_cmod_a7.py
litex_boards/platforms/digilent_genesys2.py
litex_boards/platforms/digilent_nexys4.py
litex_boards/platforms/digilent_nexys4ddr.py
litex_boards/platforms/digilent_nexys_video.py
litex_boards/platforms/digilent_pynq_z1.py
litex_boards/platforms/digilent_zedboard.py
litex_boards/platforms/digilent_zybo_z7.py
litex_boards/platforms/ebaz4205.py
litex_boards/platforms/efinix_t8f81_dev_kit.py
