Metadata-Version: 2.1
Name: litex-boards
Version: 2023.12
Summary: LiteX supported boards
Home-page: http://enjoy-digital.fr
Download-URL: https://github.com/litex-hub/litex-boards
Author: Florent Kermarrec
Author-email: florent@enjoy-digital.fr
License: BSD
Requires-Python: ~=3.7
License-File: LICENSE
Requires-Dist: litex
